tikotapi.py
tikotapi-1.0.8.dist-info/WHEEL
tikotapi-1.0.8.dist-info/METADATA
tikotapi-1.0.8.dist-info/RECORD
