Metadata-Version: 2.1
Name: tikotapi
Version: 1.0.8
Summary: Only using services (TikOt Musicaly)
Author: tikotstudio
Author-email: tikotstudio@yandex.ru
Requires-Python: >=3.7,<4.0
Classifier: Programming Language :: Python :: 3
Classifier: Programming Language :: Python :: 3.7
Classifier: Programming Language :: Python :: 3.8
Classifier: Programming Language :: Python :: 3.9
